ledger/__init__.py
ledger/admin.py
ledger/app_settings.py
ledger/apps.py
ledger/auth_hooks.py
ledger/checks.py
ledger/constants.py
ledger/decorators.py
ledger/errors.py
ledger/forms.py
ledger/hooks.py
ledger/providers.py
ledger/tasks.py
ledger/urls.py
ledger/api/__init__.py
ledger/api/helpers.py
ledger/api/schema.py
ledger/api/api_helper/planetary_helper.py
ledger/api/ledger/__init__.py
ledger/api/ledger/admin.py
ledger/api/ledger/planetary.py
ledger/docs/information.md
ledger/docs/images/preview1.png
ledger/docs/images/preview2.png
ledger/docs/images/preview3.png
ledger/docs/images/preview4.png
ledger/docs/images/preview5.png
ledger/docs/images/preview6.png
ledger/helpers/__init__.py
ledger/helpers/alliance.py
ledger/helpers/billboard.py
ledger/helpers/character.py
ledger/helpers/core.py
ledger/helpers/corporation.py
ledger/helpers/data_exporter.py
ledger/helpers/discord.py
ledger/helpers/ref_type.py
ledger/locale/__init__.py
ledger/locale/django.pot
ledger/locale/cs_CZ/LC_MESSAGES/django.mo
ledger/locale/cs_CZ/LC_MESSAGES/django.po
ledger/locale/de/LC_MESSAGES/django.mo
ledger/locale/de/LC_MESSAGES/django.po
ledger/locale/es/LC_MESSAGES/django.mo
ledger/locale/es/LC_MESSAGES/django.po
ledger/locale/fr_FR/LC_MESSAGES/django.mo
ledger/locale/fr_FR/LC_MESSAGES/django.po
ledger/locale/it_IT/LC_MESSAGES/django.mo
ledger/locale/it_IT/LC_MESSAGES/django.po
ledger/locale/ja/LC_MESSAGES/django.mo
ledger/locale/ja/LC_MESSAGES/django.po
ledger/locale/ko_KR/LC_MESSAGES/django.mo
ledger/locale/ko_KR/LC_MESSAGES/django.po
ledger/locale/nl_NL/LC_MESSAGES/django.mo
ledger/locale/nl_NL/LC_MESSAGES/django.po
ledger/locale/pl_PL/LC_MESSAGES/django.mo
ledger/locale/pl_PL/LC_MESSAGES/django.po
ledger/locale/ru/LC_MESSAGES/django.mo
ledger/locale/ru/LC_MESSAGES/django.po
ledger/locale/sk/LC_MESSAGES/django.mo
ledger/locale/sk/LC_MESSAGES/django.po
ledger/locale/uk/LC_MESSAGES/django.mo
ledger/locale/uk/LC_MESSAGES/django.po
ledger/locale/zh_Hans/LC_MESSAGES/django.mo
aa_ledger-1.0.3.dist-info/METADATA
aa_ledger-1.0.3.dist-info/WHEEL
aa_ledger-1.0.3.dist-info/licenses/LICENSE
aa_ledger-1.0.3.dist-info/RECORD
